kube_api/__init__.py
kube_api/config.py
kube_api/jobs.py
kube_api/namespaces.py
kube_api/pods.py
kube_api/utils.py
kube_api/volumeclaims.py
kube_api-0.1.65.dist-info/METADATA
kube_api-0.1.65.dist-info/WHEEL
kube_api-0.1.65.dist-info/top_level.txt
kube_api-0.1.65.dist-info/RECORD
