Metadata-Version: 2.1
Name: kube_api
Version: 0.1.65
Summary: A simple Kubernetes Python API
Home-page: https://github.com/labdave/kube_api
Author: Qiu Qin
Author-email: qiuosier@gmail.com
Classifier: Programming Language :: Python :: 3
Classifier: License :: OSI Approved :: MIT License
Classifier: Operating System :: OS Independent
Requires-Python: >=3.6
Requires-Dist: kubernetes
Requires-Dist: google-cloud-filestore
